x_net_email_css_inliner/__init__.py
x_net_email_css_inliner/inliner.py
x_net_email_css_inliner/tests/__init__.py
x_net_email_css_inliner/tests/test_inliner.py
x_net_email_css_inliner/tests/html/example.css
x_net_email_css_inliner/tests/html/example.html
x_net_email_css_inliner-1.0.2.dist-info/LICENSE
x_net_email_css_inliner-1.0.2.dist-info/METADATA
x_net_email_css_inliner-1.0.2.dist-info/WHEEL
x_net_email_css_inliner-1.0.2.dist-info/top_level.txt
x_net_email_css_inliner-1.0.2.dist-info/RECORD
