Metadata-Version: 2.1
Name: x-net-email-css-inliner
Version: 1.0.2
Summary: An Email CSS Inliner to inline a external CSS to HTML
Home-page: https://github.com/x-net-services/x-net-email-css-inliner
Author: X-Net Services GmbH
Author-email: support-software@x-net.at
License: MIT
Platform: UNKNOWN
Classifier: License :: OSI Approved :: MIT License
Classifier: Programming Language :: Python :: 3.6
Classifier: Topic :: Internet :: WWW/HTTP
Requires-Python: >=3.6
Requires-Dist: beautifulsoup4 (==4.9.3)
Requires-Dist: requests (==2.24.0)
Requires-Dist: tinycss2 (==1.0.2)
